pyshielder/__init__.py
pyshielder/core.py
pyshielder-1.0.4.dist-info/licenses/LICENSE
pyshielder-1.0.4.dist-info/METADATA
pyshielder-1.0.4.dist-info/WHEEL
pyshielder-1.0.4.dist-info/entry_points.txt
pyshielder-1.0.4.dist-info/top_level.txt
pyshielder-1.0.4.dist-info/RECORD
