Metadata-Version: 2.4
Name: pyshielder
Version: 1.0.4
Summary: A robust tool for Python code obfuscation and encryption using Cython.
Home-page: https://github.com/PythonTodayz/pyshielder
Author: PythonToday
Author-email: pythontodayz@gmail.com
Classifier: Programming Language :: Python :: 3
Classifier: License :: OSI Approved :: MIT License
Classifier: Operating System :: OS Independent
Classifier: Topic :: Security
Classifier: Topic :: Software Development :: Build Tools
Requires-Python: >=3.6
License-File: LICENSE
Requires-Dist: Cython
Dynamic: author
Dynamic: author-email
Dynamic: classifier
Dynamic: description
Dynamic: description-content-type
Dynamic: home-page
Dynamic: license-file
Dynamic: requires-dist
Dynamic: requires-python
Dynamic: summary
